pybaht/__init__.py
pybaht/__main__.py
pybaht/bahttext.py
pybaht-0.2.0.dist-info/LICENSE
pybaht-0.2.0.dist-info/METADATA
pybaht-0.2.0.dist-info/WHEEL
pybaht-0.2.0.dist-info/entry_points.txt
pybaht-0.2.0.dist-info/top_level.txt
pybaht-0.2.0.dist-info/RECORD
