Metadata-Version: 2.1
Name: pybaht
Version: 0.2.0
Summary: Baht library for Python
Home-page: https://github.com/jojoee/pybaht
Author: Nathachai Thongniran
Author-email: inid3a@gmail.com
License: MIT
Classifier: License :: OSI Approved :: MIT License
Classifier: Programming Language :: Python :: 3
Classifier: Programming Language :: Python :: 3.7
License-File: LICENSE
